readit/__init__.py
readit/cli.py
readit/database.py
readit/view.py
readit-1.0.3.dist-info/LICENSE
readit-1.0.3.dist-info/METADATA
readit-1.0.3.dist-info/WHEEL
readit-1.0.3.dist-info/entry_points.txt
readit-1.0.3.dist-info/top_level.txt
readit-1.0.3.dist-info/RECORD
