Metadata-Version: 2.1
Name: readit
Version: 1.0.3
Summary: Readit - Command Line Bookmark Manager Tool
Home-page: https://github.com/projectreadit/readit
Author: Ganesh, Shital, Daivshala
Author-email: ganeshhubale03@gmail.com
License: GNU General Public License v3.0
Keywords: clitool,bookmark,readit
Classifier: Development Status :: 4 - Beta
Classifier: Programming Language :: Python
Classifier: Programming Language :: Python :: 3.6
Classifier: Programming Language :: Python :: 3.7
Classifier: Programming Language :: Python :: 3.8
Classifier: Environment :: Console
Classifier: Topic :: Internet
Classifier: Topic :: Utilities
Requires-Python: >=3.6
License-File: LICENSE
Requires-Dist: beautifultable
Requires-Dist: click
Requires-Dist: requests
Provides-Extra: dev
Requires-Dist: pre-commit ; extra == 'dev'
Requires-Dist: readme-renderer ; extra == 'dev'
Provides-Extra: test
Requires-Dist: pytest ; extra == 'test'
Requires-Dist: pytest-mock ; extra == 'test'
